any_gold/__init__.py
any_gold/image/deepglobe.py
any_gold/image/isic2018.py
any_gold/image/kpi.py
any_gold/image/mvtec_ad.py
any_gold/image/plantseg.py
any_gold/tools/image/connected_component.py
any_gold/tools/image/fiftyone_conversion.py
any_gold/tools/image/stats.py
any_gold/utils/__init__.py
any_gold/utils/dataset.py
any_gold/utils/hugging_face.py
any_gold/utils/kaggle.py
any_gold/utils/synapse.py
any_gold/utils/zenodo.py
any_gold-0.2.1.dist-info/licenses/LICENSE
any_gold-0.2.1.dist-info/METADATA
any_gold-0.2.1.dist-info/WHEEL
any_gold-0.2.1.dist-info/top_level.txt
any_gold-0.2.1.dist-info/RECORD
