Metadata-Version: 2.4
Name: any-gold
Version: 0.2.1
Summary: Custom PyTorch Dataset implementations for publicly available datasets across various modalities
Author-email: goldener-data <yann.chene.tni@gmail.com>
License-Expression: Apache-2.0
Project-URL: Homepage, https://github.com/goldener-data/any-gold
Project-URL: Repository, https://github.com/goldener-data/any-gold
Project-URL: Issues, https://github.com/goldener-data/any-gold/issues
Classifier: Development Status :: 4 - Beta
Classifier: Intended Audience :: Developers
Classifier: Intended Audience :: Science/Research
Classifier: Programming Language :: Python :: 3.13
Classifier: Topic :: Scientific/Engineering :: Artificial Intelligence
Requires-Python: >=3.10
License-File: LICENSE
Requires-Dist: torch
Requires-Dist: torchvision
Requires-Dist: pathlib
Requires-Dist: pandas
Requires-Dist: numpy
Requires-Dist: datasets
Requires-Dist: kagglehub
Requires-Dist: zenodo-client
Requires-Dist: synapseclient
Requires-Dist: opencv-python
Provides-Extra: dev
Requires-Dist: pytest; extra == "dev"
Requires-Dist: pre-commit; extra == "dev"
Requires-Dist: ruff; extra == "dev"
Requires-Dist: mypy; extra == "dev"
Requires-Dist: pandas-stubs; extra == "dev"
Requires-Dist: types-tqdm; extra == "dev"
Provides-Extra: tools
Requires-Dist: fiftyone; extra == "tools"
Dynamic: license-file
